release.py
setup.py
taskcoach.py
TaskCoach.egg-info/PKG-INFO
TaskCoach.egg-info/SOURCES.txt
TaskCoach.egg-info/dependency_links.txt
TaskCoach.egg-info/top_level.txt
buildlib/__init__.py
buildlib/bdist_deb.py
buildlib/bdist_portable_base.py
buildlib/bdist_portableapps.py
buildlib/bdist_rpm_fedora.py
buildlib/bdist_rpm_opensuse.py
buildlib/bdist_winpenpack.py
buildlib/clean.py
taskcoachlib/__init__.py
taskcoachlib/operating_system.py
taskcoachlib/render.py
taskcoachlib/application/__init__.py
taskcoachlib/application/application.py
taskcoachlib/changes/__init__.py
taskcoachlib/changes/monitor.py
taskcoachlib/changes/sync.py
taskcoachlib/command/__init__.py
taskcoachlib/command/attachmentCommands.py
taskcoachlib/command/base.py
taskcoachlib/command/categorizableCommands.py
taskcoachlib/command/categoryCommands.py
taskcoachlib/command/clipboard.py
taskcoachlib/command/effortCommands.py
taskcoachlib/command/noteCommands.py
taskcoachlib/command/taskCommands.py
taskcoachlib/config/__init__.py
taskcoachlib/config/defaults.py
taskcoachlib/config/options.py
taskcoachlib/config/settings.py
taskcoachlib/domain/__init__.py
taskcoachlib/domain/attachment/__init__.py
taskcoachlib/domain/attachment/attachment.py
taskcoachlib/domain/attachment/attachmentlist.py
taskcoachlib/domain/attachment/attachmentowner.py
taskcoachlib/domain/attachment/sorter.py
taskcoachlib/domain/attribute/__init__.py
taskcoachlib/domain/attribute/color/__init__.py
taskcoachlib/domain/attribute/color/mixer.py
taskcoachlib/domain/attribute/font/__init__.py
taskcoachlib/domain/attribute/font/mixer.py
taskcoachlib/domain/attribute/icon/__init__.py
taskcoachlib/domain/base/__init__.py
taskcoachlib/domain/base/attribute.py
taskcoachlib/domain/base/collection.py
taskcoachlib/domain/base/filter.py
taskcoachlib/domain/base/object.py
taskcoachlib/domain/base/owner.py
taskcoachlib/domain/base/sorter.py
taskcoachlib/domain/categorizable/__init__.py
taskcoachlib/domain/categorizable/categorizable.py
taskcoachlib/domain/categorizable/categorizablecontainer.py
taskcoachlib/domain/category/__init__.py
taskcoachlib/domain/category/category.py
